tradingstrategy/__init__.py
tradingstrategy/analysis/__init__.py
tradingstrategy/analysis/portfolioanalyzer.py
tradingstrategy/analysis/profitdistribution.py
tradingstrategy/analysis/tradeanalyzer.py
tradingstrategy/analysis/tradehint.py
tradingstrategy/binance/constants.py
tradingstrategy/binance/downloader.py
tradingstrategy/binance/utils.py
tradingstrategy/caip.py
tradingstrategy/candle.py
tradingstrategy/chain.py
tradingstrategy/chains/.ci/kontinuum.json
tradingstrategy/chains/.git
tradingstrategy/chains/.github/ISSUE_TEMPLATE/add-new-chain---network-id.md
tradingstrategy/chains/.github/ISSUE_TEMPLATE/other.md
tradingstrategy/chains/.github/dependabot.yml
tradingstrategy/chains/.github/workflows/build_and_deploy.yml
tradingstrategy/chains/.gitignore
tradingstrategy/chains/LICENSE
tradingstrategy/chains/README.md
tradingstrategy/chains/_data/chains/deprecated/eip155-218.json
tradingstrategy/chains/_data/chains/eip155-1.json
tradingstrategy/chains/_data/chains/eip155-10.json
tradingstrategy/chains/_data/chains/eip155-100.json
tradingstrategy/chains/_data/chains/eip155-10000.json
tradingstrategy/chains/_data/chains/eip155-100000.json
tradingstrategy/chains/_data/chains/eip155-100001.json
tradingstrategy/chains/_data/chains/eip155-100002.json
tradingstrategy/chains/_data/chains/eip155-100003.json
tradingstrategy/chains/_data/chains/eip155-100004.json
tradingstrategy/chains/_data/chains/eip155-100005.json
tradingstrategy/chains/_data/chains/eip155-100006.json
tradingstrategy/chains/_data/chains/eip155-100007.json
tradingstrategy/chains/_data/chains/eip155-100008.json
tradingstrategy/chains/_data/chains/eip155-10001.json
tradingstrategy/chains/_data/chains/eip155-1001.json
tradingstrategy/chains/_data/chains/eip155-1007.json
tradingstrategy/chains/_data/chains/eip155-101.json
tradingstrategy/chains/_data/chains/eip155-1010.json
tradingstrategy/chains/_data/chains/eip155-10101.json
tradingstrategy/chains/_data/chains/eip155-1012.json
trading_strategy-0.22.11.dist-info/LICENSE.txt
trading_strategy-0.22.11.dist-info/METADATA
trading_strategy-0.22.11.dist-info/WHEEL
trading_strategy-0.22.11.dist-info/RECORD
