Metadata-Version: 2.1
Name: trading-strategy
Version: 0.22.11
Summary: Algorithmic trading, token and cryptocurrency DEX trading data, for Uniswap, Aave, PancakeSwap, Sushi, Trader Joe, others
Home-page: https://tradingstrategy.ai
License: AGPL
Keywords: algorithmic trading,ethereum,polygon,avalanche,aave,arbitrum,cryptocurrency,uniswap,quantitative finance,binance,blockchain,pancakeswap,polygon,web3
Author: Mikko Ohtamaa
Author-email: mikko@tradingstrategy.ai
Requires-Python: >=3.10,<=3.12
Classifier: License :: Other/Proprietary License
Classifier: Programming Language :: Python :: 3
Classifier: Programming Language :: Python :: 3.10
Classifier: Programming Language :: Python :: 3.11
Classifier: Programming Language :: Python :: 3.12
Provides-Extra: backtrader
Provides-Extra: direct-feed
Provides-Extra: qstrader
Requires-Dist: coloredlogs (>=15.0.1,<16.0.0)
Requires-Dist: dash (>=2.7.1,<3.0.0) ; extra == "direct-feed"
Requires-Dist: dataclasses-json (>=0.5.4,<0.6.0)
Requires-Dist: filelock (>=3.12.4,<4.0.0)
Requires-Dist: jsonlines (>=3.1.0,<4.0.0)
Requires-Dist: pandas (<2.2)
Requires-Dist: plotly (>=5.1.0,<6.0.0)
Requires-Dist: pyarrow (>=14.0.1,<15.0.0)
Requires-Dist: requests (>=2.28.1,<3.0.0)
Requires-Dist: scipy (>=1.6.1,<2.0.0) ; extra == "qstrader"
Requires-Dist: tqdm (>=4.61.2,<5.0.0)
Requires-Dist: tqdm-loggable (>=0.2)
Requires-Dist: trading-strategy-backtrader (>=0.1,<0.2) ; extra == "backtrader"
Requires-Dist: trading-strategy-qstrader (>=0.5.0,<0.6.0) ; extra == "qstrader"
Requires-Dist: typer (>=0.7.0,<0.8.0) ; extra == "direct-feed"
Requires-Dist: web3-ethereum-defi[data,test] (>=0.24.1) ; extra == "direct-feed"
Project-URL: Changelog, https://github.com/tradingstrategy-ai/web3-ethereum-defi/blob/master/CHANGELOG.md
Project-URL: Documentation, https://tradingstrategy.ai/docs/
Project-URL: Discord, https://discord.gg/5M88m9nM8H
Project-URL: Repository, https://github.com/tradingstrategy-ai/trading-strategy
Project-URL: Sponsor, https://tradingstrategy.ai
Project-URL: Twitter, https://twitter.com/tradingprotocol
Project-URL: Youtube, https://www.youtube.com/@tradingstrategyprotocol
